fpicker.cp313-win_amd64.pyd
fpicker-1.0.2.dist-info/LICENSE
fpicker-1.0.2.dist-info/METADATA
fpicker-1.0.2.dist-info/WHEEL
fpicker-1.0.2.dist-info/top_level.txt
fpicker-1.0.2.dist-info/RECORD
